Metadata-Version: 2.1
Name: sentry-dingding-cp
Version: 0.0.2
Summary: sentry-dingding-cp
Home-page: UNKNOWN
Author: wv
Author-email: 1999wuwei@gmail.com
License: MIT
Keywords: cp sentry dingding
Platform: UNKNOWN
Classifier: Programming Language :: Python :: 2.7
Classifier: License :: OSI Approved :: MIT License
